gutenbergpy/__init__.py
gutenbergpy/gutenbergcache.py
gutenbergpy/gutenbergcachesettings.py
gutenbergpy/orderedset.py
gutenbergpy/textget.py
gutenbergpy/utils.py
gutenbergpy/caches/__init__.py
gutenbergpy/caches/cache.py
gutenbergpy/caches/gutenbergindex.db.sql
gutenbergpy/caches/gutenbergindex_indices.db.sql
gutenbergpy/caches/mongodbcache.py
gutenbergpy/caches/sqlitecache.py
gutenbergpy/parse/__init__.py
gutenbergpy/parse/book.py
gutenbergpy/parse/cachefields.py
gutenbergpy/parse/parseitem.py
gutenbergpy/parse/parseitemfile.py
gutenbergpy/parse/parseitemtitles.py
gutenbergpy/parse/rdfparser.py
gutenbergpy/parse/rdfparseresults.py
gutenbergpy-0.3.5.dist-info/LICENSE.txt
gutenbergpy-0.3.5.dist-info/METADATA
gutenbergpy-0.3.5.dist-info/WHEEL
gutenbergpy-0.3.5.dist-info/top_level.txt
gutenbergpy-0.3.5.dist-info/RECORD
