Metadata-Version: 2.1
Name: gutenbergpy
Version: 0.3.5
Summary: Library to create and interogate local cache for Project Gutenberg
Home-page: https://github.com/raduangelescu/gutenbergpy
Download-URL: http://pypi.python.org/pypi/gutenbergpy
Author: Radu Angelescu
Author-email: raduangelescu@gmail.com
License: LICENSE.txt
Project-URL: Bug Tracker, http://pypi.python.org/pypi/gutenbergpy/issues
Classifier: Programming Language :: Python :: 3
Classifier: License :: OSI Approved :: MIT License
Classifier: Operating System :: OS Independent
Requires-Python: >=3.6
License-File: LICENSE.txt
